PalmSens-stubs/__init__.pyi
PalmSens-stubs/py.typed
PalmSens-stubs/Analysis/__init__.pyi
PalmSens-stubs/Annotations/__init__.pyi
PalmSens-stubs/AuxInput/__init__.pyi
PalmSens-stubs/Calculations/__init__.pyi
PalmSens-stubs/Calibration/__init__.pyi
PalmSens-stubs/Comm/__init__.pyi
PalmSens-stubs/Core/Data/__init__.pyi
PalmSens-stubs/Core/Techniques/__init__.pyi
PalmSens-stubs/CorrosionTechniques/__init__.pyi
PalmSens-stubs/Data/__init__.pyi
PalmSens-stubs/DataFiles/__init__.pyi
PalmSens-stubs/Devices/__init__.pyi
PalmSens-stubs/Devices/Simulated/__init__.pyi
PalmSens-stubs/ExternalInterfaces/Reporting/__init__.pyi
PalmSens-stubs/Fitting/__init__.pyi
PalmSens-stubs/Fitting/Models/__init__.pyi
PalmSens-stubs/Fitting/Models/Circuits/__init__.pyi
PalmSens-stubs/Fitting/Models/Circuits/Elements/__init__.pyi
PalmSens-stubs/Plottables/__init__.pyi
PalmSens-stubs/Simulated/__init__.pyi
PalmSens-stubs/Techniques/__init__.pyi
PalmSens-stubs/Techniques/Impedance/__init__.pyi
PalmSens-stubs/Units/__init__.pyi
pypalmsens/__init__.py
pypalmsens/_fitting.py
pypalmsens/_helpers.py
pypalmsens/_io.py
pypalmsens/data.py
pypalmsens/fitting.py
pypalmsens/mixed_mode.py
pypalmsens/settings.py
pypalmsens/_data/__init__.py
pypalmsens/_data/curve.py
pypalmsens/_data/data_array.py
pypalmsens/_data/dataset.py
pypalmsens/_data/eisdata.py
pypalmsens/_data/measurement.py
pypalmsens/_data/peak.py
pypalmsens/_data/shared.py
pypalmsens/_instruments/__init__.py
pypalmsens/_instruments/callback.py
pypalmsens/_instruments/instrument_manager.py
pypalmsens/_instruments/instrument_manager_async.py
pypalmsens/_instruments/instrument_pool.py
pypalmsens/_instruments/instrument_pool_async.py
pypalmsens/_instruments/measurement_manager_async.py
pypalmsens/_instruments/shared.py
pypalmsens/_libpalmsens/__init__.py
pypalmsens/_libpalmsens/mono.py
pypalmsens/_libpalmsens/windows.py
pypalmsens/_libpalmsens/linux-arm64/PalmSens.Core.Linux.deps.json
pypalmsens/_libpalmsens/linux-arm64/PalmSens.Core.Linux.dll
pypalmsens-1.6.0.dist-info/licenses/LICENSE
pypalmsens-1.6.0.dist-info/METADATA
pypalmsens-1.6.0.dist-info/WHEEL
pypalmsens-1.6.0.dist-info/top_level.txt
pypalmsens-1.6.0.dist-info/RECORD
