Metadata-Version: 2.4
Name: PyPalmSens
Version: 1.6.0
Summary: Python SDK for PalmSens instruments
Author-email: Palmsens BV <info@palmsens.com>
License-Expression: LicenseRef-Modified-BSD-3-Clause-PalmSens
Project-URL: homepage, https://github.com/palmsens/palmsens_sdk
Project-URL: issues, https://github.com/palmsens/palmsens_sdk/issues
Project-URL: documentation, https://sdk.palmsens.com/python/latest
Project-URL: changelog, https://github.com/palmsens/palmsens_sdk/releases
Keywords: electrochemistry,data-analysis,voltammetry,potentiometry,impedance-specroscopy
Classifier: Development Status :: 5 - Production/Stable
Classifier: Intended Audience :: Science/Research
Classifier: Natural Language :: English
Classifier: Operating System :: OS Independent
Classifier: Programming Language :: Python :: 3
Classifier: Programming Language :: Python :: 3.10
Classifier: Programming Language :: Python :: 3.11
Classifier: Programming Language :: Python :: 3.12
Classifier: Programming Language :: Python :: 3.13
Classifier: Topic :: Scientific/Engineering
Requires-Python: >=3.10
License-File: LICENSE
Requires-Dist: pydantic
Requires-Dist: numpy
Requires-Dist: pythonnet
Requires-Dist: typing-extensions
Provides-Extra: develop
Requires-Dist: bump-my-version; extra == "develop"
Requires-Dist: coverage; extra == "develop"
Requires-Dist: griffe2md; extra == "develop"
Requires-Dist: pre-commit; extra == "develop"
Requires-Dist: pytest; extra == "develop"
Requires-Dist: pytest-asyncio; extra == "develop"
Provides-Extra: publishing
Requires-Dist: twine; extra == "publishing"
Requires-Dist: wheel; extra == "publishing"
Requires-Dist: build; extra == "publishing"
Dynamic: license-file
